{
  "servantAscensionData": [{
    "combatantData": {
      "id": "servant286",
      "rarity": 4,
      "fateClass": "ARCHER",
      "gender": "FEMALE",
      "alignments": ["NEUTRAL", "SUMMER"],
      "attribute": "MAN",
      "traits": ["ILLYA", "HOMINIDAE_SERVANT", "LIVING_HUMAN", "CHILD_SERVANT", "SUMMER_SERVANTS", "HUMANOID", "WEAK_TO_ENUMA_ELISH"],
      "deathRate": 0.315
    },
    "defenseNpRate": 0.03,
    "criticalStarWeight": 148,
    "commandCardData": [{
      "commandCardType": "QUICK",
      "hitsData": [10, 20, 30, 40],
      "npRate": 0.0063,
      "criticalStarGen": 0.08
    }, {
      "commandCardType": "QUICK",
      "hitsData": [10, 20, 30, 40],
      "npRate": 0.0063,
      "criticalStarGen": 0.08
    }, {
      "commandCardType": "ARTS",
      "hitsData": [16, 33, 51],
      "npRate": 0.0063,
      "criticalStarGen": 0.08
    }, {
      "commandCardType": "ARTS",
      "hitsData": [16, 33, 51],
      "npRate": 0.0063,
      "criticalStarGen": 0.08
    }, {
      "commandCardType": "BUSTER",
      "hitsData": [16, 33, 51],
      "npRate": 0.0063,
      "criticalStarGen": 0.08
    }],
    "activeSkillUpgrades": [{
      "activeSkillData": [{
        "baseCoolDown": 7,
        "effects": [{
          "type": "GrantBuff",
          "target": "SELF",
          "buffData": [{
            "type": "CommandCardBuff",
            "numTurnsActive": 3,
            "applyCondition": {
              "type": "CardTypeEquals",
              "value": "QUICK"
            },
            "values": [0.1, 0.11, 0.12, 0.13, 0.14, 0.15, 0.16, 0.17, 0.18, 0.2],
            "buffIcon": "quickUp"
          }]
        }, {
          "type": "GrantBuff",
          "target": "SELF",
          "buffData": [{
            "type": "CriticalStarWeightBuff",
            "numTurnsActive": 1,
            "applyCondition": {
              "type": "CardTypeEquals",
              "value": "QUICK"
            },
            "values": [3.0, 3.2, 3.4, 3.6, 3.8, 4.0, 4.2, 4.4, 4.6, 5.0],
            "buffIcon": "starWeightUp"
          }]
        }, {
          "type": "GrantBuff",
          "target": "SELF",
          "buffData": [{
            "type": "CriticalDamageBuff",
            "numTurnsActive": 1,
            "values": [0.5, 0.55, 0.6, 0.65, 0.7, 0.75, 0.8, 0.85, 0.9, 1.0],
            "buffIcon": "critDamageUp"
          }]
        }],
        "iconName": "quickUp"
      }]
    }, {
      "activeSkillData": [{
        "baseCoolDown": 8,
        "effects": [{
          "type": "GrantBuff",
          "target": "SELF",
          "buffData": [{
            "type": "Invincible",
            "numTurnsActive": 3,
            "numTimesActive": 1,
            "buffIcon": "invincible"
          }]
        }, {
          "type": "GrantBuff",
          "target": "SELF",
          "buffData": [{
            "type": "NpGenerationBuff",
            "numTurnsActive": 3,
            "values": [0.2, 0.21, 0.22, 0.23, 0.24, 0.25, 0.26, 0.27, 0.28, 0.3],
            "buffIcon": "npGainUp"
          }]
        }, {
          "type": "GrantBuff",
          "target": "ALL_ALLIES",
          "applyCondition": {
            "type": "TargetsHaveTrait",
            "value": "CHILD_SERVANT",
            "target": "EFFECT_TARGET"
          },
          "buffData": [{
            "type": "AttackBuff",
            "numTurnsActive": 3,
            "values": [0.1, 0.11, 0.12, 0.13, 0.14, 0.15, 0.16, 0.17, 0.18, 0.2],
            "buffIcon": "attackUp"
          }]
        }],
        "iconName": "invincible"
      }]
    }, {
      "activeSkillData": [{
        "baseCoolDown": 7,
        "effects": [{
          "type": "NpChange",
          "target": "SELF",
          "values": [0.2, 0.21, 0.22, 0.23, 0.24, 0.25, 0.26, 0.27, 0.28, 0.3]
        }, {
          "type": "GrantBuff",
          "target": "SELF",
          "buffData": [{
            "type": "CriticalDamageBuff",
            "numTurnsActive": 3,
            "values": [0.3, 0.32, 0.34, 0.36, 0.38, 0.4, 0.42, 0.44, 0.46, 0.5],
            "buffIcon": "critDamageUp"
          }]
        }, {
          "type": "GrantBuff",
          "target": "SELF",
          "buffData": [{
            "type": "EndOfTurnEffect",
            "subEffects": [{
              "type": "HpChange",
              "target": "SELF",
              "intValues": [500]
            }],
            "customTraits": ["POSITIVE_BUFF"],
            "hasCustomTraits": true,
            "buffIcon": "hpPerTurn"
          }],
          "probabilities": [0.7]
        }],
        "iconName": "npGain"
      }]
    }],
    "passiveSkillData": [{
      "effects": [{
        "type": "GrantBuff",
        "target": "SELF",
        "buffData": [{
          "type": "DebuffResist",
          "values": [0.2],
          "buffIcon": "debuffResistUp"
        }]
      }],
      "iconName": "magicResistance"
    }, {
      "effects": [{
        "type": "GrantBuff",
        "target": "SELF",
        "buffData": [{
          "type": "CriticalDamageBuff",
          "values": [0.08],
          "buffIcon": "critDamageUp"
        }]
      }],
      "iconName": "independent"
    }, {
      "effects": [{
        "type": "GrantBuff",
        "target": "SELF",
        "buffData": [{
          "type": "EndOfTurnEffect",
          "subEffects": [{
            "type": "NpChange",
            "target": "SELF",
            "values": [0.03]
          }],
          "buffIcon": "npPerTurn"
        }]
      }],
      "iconName": "npPerTurn"
    }],
    "appendSkillData": [{
      "effects": [{
        "type": "GrantBuff",
        "target": "SELF",
        "buffData": [{
          "type": "CommandCardBuff",
          "applyCondition": {
            "type": "CardTypeEquals",
            "value": "EXTRA"
          },
          "values": [0.3, 0.32, 0.34, 0.36, 0.38, 0.4, 0.42, 0.44, 0.46, 0.5],
          "buffIcon": "specialDamageUp"
        }]
      }],
      "iconName": "specialAttackUp"
    }, {
      "effects": [{
        "type": "NpChange",
        "target": "SELF",
        "values": [0.1, 0.11, 0.12, 0.13, 0.14, 0.15, 0.16, 0.17, 0.18, 0.2]
      }],
      "iconName": "npGain"
    }, {
      "effects": [{
        "type": "GrantBuff",
        "target": "SELF",
        "buffData": [{
          "type": "AttackBuff",
          "applyCondition": {
            "type": "TargetsHaveClass",
            "value": "ARCHER",
            "target": "DEFENDER"
          },
          "values": [0.2, 0.21, 0.22, 0.23, 0.24, 0.25, 0.26, 0.27, 0.28, 0.3],
          "buffIcon": "attackUp"
        }]
      }],
      "iconName": "attackUp"
    }],
    "servantStatusData": [{
      "lv": 1,
      "HP": 1746,
      "ATK": 1683
    }, {
      "lv": 2,
      "HP": 1920,
      "ATK": 1842
    }, {
      "lv": 3,
      "HP": 2103,
      "ATK": 2011
    }, {
      "lv": 4,
      "HP": 2286,
      "ATK": 2179
    }, {
      "lv": 5,
      "HP": 2470,
      "ATK": 2347
    }, {
      "lv": 6,
      "HP": 2644,
      "ATK": 2507
    }, {
      "lv": 7,
      "HP": 2827,
      "ATK": 2675
    }, {
      "lv": 8,
      "HP": 3002,
      "ATK": 2835
    }, {
      "lv": 9,
      "HP": 3176,
      "ATK": 2995
    }, {
      "lv": 10,
      "HP": 3350,
      "ATK": 3155
    }, {
      "lv": 11,
      "HP": 3515,
      "ATK": 3307
    }, {
      "lv": 12,
      "HP": 3680,
      "ATK": 3458
    }, {
      "lv": 13,
      "HP": 3845,
      "ATK": 3610
    }, {
      "lv": 14,
      "HP": 4010,
      "ATK": 3761
    }, {
      "lv": 15,
      "HP": 4166,
      "ATK": 3904
    }, {
      "lv": 16,
      "HP": 4313,
      "ATK": 4039
    }, {
      "lv": 17,
      "HP": 4468,
      "ATK": 4182
    }, {
      "lv": 18,
      "HP": 4606,
      "ATK": 4308
    }, {
      "lv": 19,
      "HP": 4753,
      "ATK": 4443
    }, {
      "lv": 20,
      "HP": 4881,
      "ATK": 4560
    }, {
      "lv": 21,
      "HP": 5018,
      "ATK": 4687
    }, {
      "lv": 22,
      "HP": 5138,
      "ATK": 4796
    }, {
      "lv": 23,
      "HP": 5257,
      "ATK": 4905
    }, {
      "lv": 24,
      "HP": 5376,
      "ATK": 5015
    }, {
      "lv": 25,
      "HP": 5477,
      "ATK": 5107
    }, {
      "lv": 26,
      "HP": 5587,
      "ATK": 5208
    }, {
      "lv": 27,
      "HP": 5679,
      "ATK": 5293
    }, {
      "lv": 28,
      "HP": 5770,
      "ATK": 5377
    }, {
      "lv": 29,
      "HP": 5853,
      "ATK": 5452
    }, {
      "lv": 30,
      "HP": 5935,
      "ATK": 5528
    }, {
      "lv": 31,
      "HP": 5999,
      "ATK": 5587
    }, {
      "lv": 32,
      "HP": 6064,
      "ATK": 5646
    }, {
      "lv": 33,
      "HP": 6119,
      "ATK": 5696
    }, {
      "lv": 34,
      "HP": 6174,
      "ATK": 5747
    }, {
      "lv": 35,
      "HP": 6219,
      "ATK": 5789
    }, {
      "lv": 36,
      "HP": 6256,
      "ATK": 5823
    }, {
      "lv": 37,
      "HP": 6284,
      "ATK": 5848
    }, {
      "lv": 38,
      "HP": 6302,
      "ATK": 5865
    }, {
      "lv": 39,
      "HP": 6320,
      "ATK": 5882
    }, {
      "lv": 40,
      "HP": 6330,
      "ATK": 5890
    }, {
      "lv": 41,
      "HP": 6339,
      "ATK": 5898
    }, {
      "lv": 42,
      "HP": 6348,
      "ATK": 5907
    }, {
      "lv": 43,
      "HP": 6357,
      "ATK": 5915
    }, {
      "lv": 44,
      "HP": 6366,
      "ATK": 5924
    }, {
      "lv": 45,
      "HP": 6394,
      "ATK": 5949
    }, {
      "lv": 46,
      "HP": 6430,
      "ATK": 5983
    }, {
      "lv": 47,
      "HP": 6476,
      "ATK": 6025
    }, {
      "lv": 48,
      "HP": 6531,
      "ATK": 6075
    }, {
      "lv": 49,
      "HP": 6586,
      "ATK": 6126
    }, {
      "lv": 50,
      "HP": 6650,
      "ATK": 6185
    }, {
      "lv": 51,
      "HP": 6715,
      "ATK": 6243
    }, {
      "lv": 52,
      "HP": 6797,
      "ATK": 6319
    }, {
      "lv": 53,
      "HP": 6880,
      "ATK": 6395
    }, {
      "lv": 54,
      "HP": 6971,
      "ATK": 6479
    }, {
      "lv": 55,
      "HP": 7063,
      "ATK": 6563
    }, {
      "lv": 56,
      "HP": 7173,
      "ATK": 6664
    }, {
      "lv": 57,
      "HP": 7274,
      "ATK": 6757
    }, {
      "lv": 58,
      "HP": 7393,
      "ATK": 6866
    }, {
      "lv": 59,
      "HP": 7512,
      "ATK": 6976
    }, {
      "lv": 60,
      "HP": 7631,
      "ATK": 7085
    }, {
      "lv": 61,
      "HP": 7769,
      "ATK": 7211
    }, {
      "lv": 62,
      "HP": 7897,
      "ATK": 7329
    }, {
      "lv": 63,
      "HP": 8044,
      "ATK": 7464
    }, {
      "lv": 64,
      "HP": 8181,
      "ATK": 7590
    }, {
      "lv": 65,
      "HP": 8337,
      "ATK": 7733
    }, {
      "lv": 66,
      "HP": 8484,
      "ATK": 7868
    }, {
      "lv": 67,
      "HP": 8640,
      "ATK": 8011
    }, {
      "lv": 68,
      "HP": 8805,
      "ATK": 8162
    }, {
      "lv": 69,
      "HP": 8970,
      "ATK": 8314
    }, {
      "lv": 70,
      "HP": 9135,
      "ATK": 8465
    }, {
      "lv": 71,
      "HP": 9300,
      "ATK": 8616
    }, {
      "lv": 72,
      "HP": 9474,
      "ATK": 8776
    }, {
      "lv": 73,
      "HP": 9648,
      "ATK": 8936
    }, {
      "lv": 74,
      "HP": 9823,
      "ATK": 9096
    }, {
      "lv": 75,
      "HP": 10006,
      "ATK": 9264
    }, {
      "lv": 76,
      "HP": 10180,
      "ATK": 9424
    }, {
      "lv": 77,
      "HP": 10363,
      "ATK": 9593
    }, {
      "lv": 78,
      "HP": 10547,
      "ATK": 9761
    }, {
      "lv": 79,
      "HP": 10730,
      "ATK": 9929
    }, {
      "lv": 80,
      "HP": 10914,
      "ATK": 10098
    }, {
      "lv": 81,
      "HP": 11024,
      "ATK": 10198
    }, {
      "lv": 82,
      "HP": 11143,
      "ATK": 10308
    }, {
      "lv": 83,
      "HP": 11253,
      "ATK": 10409
    }, {
      "lv": 84,
      "HP": 11372,
      "ATK": 10518
    }, {
      "lv": 85,
      "HP": 11491,
      "ATK": 10628
    }, {
      "lv": 86,
      "HP": 11601,
      "ATK": 10729
    }, {
      "lv": 87,
      "HP": 11720,
      "ATK": 10838
    }, {
      "lv": 88,
      "HP": 11839,
      "ATK": 10947
    }, {
      "lv": 89,
      "HP": 11949,
      "ATK": 11048
    }, {
      "lv": 90,
      "HP": 12069,
      "ATK": 11158
    }, {
      "lv": 91,
      "HP": 12188,
      "ATK": 11267
    }, {
      "lv": 92,
      "HP": 12298,
      "ATK": 11368
    }, {
      "lv": 93,
      "HP": 12417,
      "ATK": 11478
    }, {
      "lv": 94,
      "HP": 12536,
      "ATK": 11587
    }, {
      "lv": 95,
      "HP": 12646,
      "ATK": 11688
    }, {
      "lv": 96,
      "HP": 12765,
      "ATK": 11797
    }, {
      "lv": 97,
      "HP": 12885,
      "ATK": 11907
    }, {
      "lv": 98,
      "HP": 12995,
      "ATK": 12008
    }, {
      "lv": 99,
      "HP": 13114,
      "ATK": 12117
    }, {
      "lv": 100,
      "HP": 13233,
      "ATK": 12226
    }, {
      "lv": 101,
      "HP": 13343,
      "ATK": 12327
    }, {
      "lv": 102,
      "HP": 13462,
      "ATK": 12437
    }, {
      "lv": 103,
      "HP": 13581,
      "ATK": 12546
    }, {
      "lv": 104,
      "HP": 13691,
      "ATK": 12647
    }, {
      "lv": 105,
      "HP": 13811,
      "ATK": 12757
    }, {
      "lv": 106,
      "HP": 13930,
      "ATK": 12866
    }, {
      "lv": 107,
      "HP": 14040,
      "ATK": 12967
    }, {
      "lv": 108,
      "HP": 14159,
      "ATK": 13076
    }, {
      "lv": 109,
      "HP": 14278,
      "ATK": 13186
    }, {
      "lv": 110,
      "HP": 14388,
      "ATK": 13287
    }, {
      "lv": 111,
      "HP": 14507,
      "ATK": 13396
    }, {
      "lv": 112,
      "HP": 14627,
      "ATK": 13506
    }, {
      "lv": 113,
      "HP": 14737,
      "ATK": 13607
    }, {
      "lv": 114,
      "HP": 14856,
      "ATK": 13716
    }, {
      "lv": 115,
      "HP": 14975,
      "ATK": 13825
    }, {
      "lv": 116,
      "HP": 15085,
      "ATK": 13926
    }, {
      "lv": 117,
      "HP": 15204,
      "ATK": 14036
    }, {
      "lv": 118,
      "HP": 15323,
      "ATK": 14145
    }, {
      "lv": 119,
      "HP": 15433,
      "ATK": 14246
    }, {
      "lv": 120,
      "HP": 15553,
      "ATK": 14355
    }],
    "noblePhantasmUpgrades": {
      "noblePhantasmData": [{
        "commandCardData": {
          "commandCardType": "QUICK",
          "hitsData": [6, 13, 20, 26, 35],
          "npRate": 0.0063,
          "criticalStarGen": 0.08
        },
        "effects": [{
          "type": "GrantBuff",
          "target": "SELF",
          "isOverchargedEffect": true,
          "buffData": [{
            "type": "CommandCardBuff",
            "numTurnsActive": 1,
            "applyCondition": {
              "type": "CardTypeEquals",
              "value": "QUICK"
            },
            "values": [0.1],
            "buffIcon": "quickUp"
          }, {
            "type": "CommandCardBuff",
            "numTurnsActive": 1,
            "applyCondition": {
              "type": "CardTypeEquals",
              "value": "QUICK"
            },
            "values": [0.2],
            "buffIcon": "quickUp"
          }, {
            "type": "CommandCardBuff",
            "numTurnsActive": 1,
            "applyCondition": {
              "type": "CardTypeEquals",
              "value": "QUICK"
            },
            "values": [0.3],
            "buffIcon": "quickUp"
          }, {
            "type": "CommandCardBuff",
            "numTurnsActive": 1,
            "applyCondition": {
              "type": "CardTypeEquals",
              "value": "QUICK"
            },
            "values": [0.4],
            "buffIcon": "quickUp"
          }, {
            "type": "CommandCardBuff",
            "numTurnsActive": 1,
            "applyCondition": {
              "type": "CardTypeEquals",
              "value": "QUICK"
            },
            "values": [0.5],
            "buffIcon": "quickUp"
          }]
        }, {
          "type": "GrantBuff",
          "target": "SELF",
          "isOverchargedEffect": true,
          "buffData": [{
            "type": "CommandCardBuff",
            "numTurnsActive": 1,
            "applyCondition": {
              "type": "CardTypeEquals",
              "value": "ARTS"
            },
            "values": [0.1],
            "buffIcon": "artsUp"
          }, {
            "type": "CommandCardBuff",
            "numTurnsActive": 1,
            "applyCondition": {
              "type": "CardTypeEquals",
              "value": "ARTS"
            },
            "values": [0.2],
            "buffIcon": "artsUp"
          }, {
            "type": "CommandCardBuff",
            "numTurnsActive": 1,
            "applyCondition": {
              "type": "CardTypeEquals",
              "value": "ARTS"
            },
            "values": [0.3],
            "buffIcon": "artsUp"
          }, {
            "type": "CommandCardBuff",
            "numTurnsActive": 1,
            "applyCondition": {
              "type": "CardTypeEquals",
              "value": "ARTS"
            },
            "values": [0.4],
            "buffIcon": "artsUp"
          }, {
            "type": "CommandCardBuff",
            "numTurnsActive": 1,
            "applyCondition": {
              "type": "CardTypeEquals",
              "value": "ARTS"
            },
            "values": [0.5],
            "buffIcon": "artsUp"
          }]
        }, {
          "type": "GrantBuff",
          "target": "SELF",
          "isOverchargedEffect": true,
          "buffData": [{
            "type": "CommandCardBuff",
            "numTurnsActive": 1,
            "applyCondition": {
              "type": "CardTypeEquals",
              "value": "BUSTER"
            },
            "values": [0.1],
            "buffIcon": "busterUp"
          }, {
            "type": "CommandCardBuff",
            "numTurnsActive": 1,
            "applyCondition": {
              "type": "CardTypeEquals",
              "value": "BUSTER"
            },
            "values": [0.2],
            "buffIcon": "busterUp"
          }, {
            "type": "CommandCardBuff",
            "numTurnsActive": 1,
            "applyCondition": {
              "type": "CardTypeEquals",
              "value": "BUSTER"
            },
            "values": [0.3],
            "buffIcon": "busterUp"
          }, {
            "type": "CommandCardBuff",
            "numTurnsActive": 1,
            "applyCondition": {
              "type": "CardTypeEquals",
              "value": "BUSTER"
            },
            "values": [0.4],
            "buffIcon": "busterUp"
          }, {
            "type": "CommandCardBuff",
            "numTurnsActive": 1,
            "applyCondition": {
              "type": "CardTypeEquals",
              "value": "BUSTER"
            },
            "values": [0.5],
            "buffIcon": "busterUp"
          }]
        }, {
          "type": "GrantBuff",
          "target": "SELF",
          "buffData": [{
            "type": "SureHit",
            "numTurnsActive": 1,
            "buffIcon": "sureHit"
          }]
        }, {
          "type": "NoblePhantasmDamage",
          "target": "ALL_ENEMIES",
          "values": [6.0, 8.0, 9.0, 9.5, 10.0]
        }],
        "noblePhantasmType": "ALL_TARGETS_NP"
      }]
    },
    "extraCard": {
      "commandCardType": "EXTRA",
      "hitsData": [10, 20, 30, 40],
      "npRate": 0.0063,
      "criticalStarGen": 0.08
    },
    "cost": 12
  }],
  "servantNum": 286
}
