{
  "servantAscensionData": [{
    "combatantData": {
      "id": "servant193",
      "rarity": 4,
      "fateClass": "LANCER",
      "gender": "FEMALE",
      "alignments": ["NEUTRAL", "GOOD"],
      "attribute": "SKY",
      "traits": ["MECHANICAL", "HUMANOID", "WEAK_TO_ENUMA_ELISH"],
      "deathRate": 0.28
    },
    "defenseNpRate": 0.04,
    "criticalStarWeight": 91,
    "commandCardData": [{
      "commandCardType": "QUICK",
      "hitsData": [10, 20, 30, 40],
      "npRate": 0.0072,
      "criticalStarGen": 0.122
    }, {
      "commandCardType": "QUICK",
      "hitsData": [10, 20, 30, 40],
      "npRate": 0.0072,
      "criticalStarGen": 0.122
    }, {
      "commandCardType": "ARTS",
      "hitsData": [16, 33, 51],
      "npRate": 0.0072,
      "criticalStarGen": 0.122
    }, {
      "commandCardType": "BUSTER",
      "hitsData": [16, 33, 51],
      "npRate": 0.0072,
      "criticalStarGen": 0.122
    }, {
      "commandCardType": "BUSTER",
      "hitsData": [16, 33, 51],
      "npRate": 0.0072,
      "criticalStarGen": 0.122
    }],
    "activeSkillUpgrades": [{
      "activeSkillData": [{
        "baseCoolDown": 7,
        "effects": [{
          "type": "GrantBuff",
          "target": "SELF",
          "buffData": [{
            "type": "CommandCardBuff",
            "numTurnsActive": 3,
            "applyCondition": {
              "type": "CardTypeEquals",
              "value": "QUICK"
            },
            "values": [0.1, 0.11, 0.12, 0.13, 0.14, 0.15, 0.16, 0.17, 0.18, 0.2],
            "buffIcon": "quickUp"
          }]
        }, {
          "type": "GrantBuff",
          "target": "SELF",
          "buffData": [{
            "type": "CommandCardBuff",
            "numTurnsActive": 3,
            "applyCondition": {
              "type": "CardTypeEquals",
              "value": "BUSTER"
            },
            "values": [0.1, 0.11, 0.12, 0.13, 0.14, 0.15, 0.16, 0.17, 0.18, 0.2],
            "buffIcon": "busterUp"
          }]
        }, {
          "type": "GrantBuff",
          "target": "SELF",
          "buffData": [{
            "type": "CriticalDamageBuff",
            "numTurnsActive": 3,
            "values": [0.2, 0.21, 0.22, 0.23, 0.24, 0.25, 0.26, 0.27, 0.28, 0.3],
            "buffIcon": "critDamageUp"
          }]
        }],
        "iconName": "quickBusterUp"
      }]
    }, {
      "activeSkillData": [{
        "baseCoolDown": 9,
        "effects": [{
          "type": "GrantBuff",
          "target": "SELF",
          "buffData": [{
            "type": "Guts",
            "numTurnsActive": 5,
            "numTimesActive": 1,
            "values": [1000.0, 1100.0, 1200.0, 1300.0, 1400.0, 1500.0, 1600.0, 1700.0, 1800.0, 2000.0],
            "buffIcon": "guts"
          }]
        }, {
          "type": "NpChange",
          "target": "SELF",
          "values": [0.1, 0.11, 0.12, 0.13, 0.14, 0.15, 0.16, 0.17, 0.18, 0.2]
        }],
        "iconName": "guts"
      }]
    }, {
      "activeSkillData": [{
        "baseCoolDown": 7,
        "effects": [{
          "type": "GrantBuff",
          "target": "SELF",
          "buffData": [{
            "type": "CriticalStarWeightBuff",
            "numTurnsActive": 1,
            "values": [3.0, 3.2, 3.4, 3.6, 3.8, 4.0, 4.2, 4.4, 4.6, 5.0],
            "buffIcon": "starWeightUp"
          }]
        }, {
          "type": "RemoveBuff",
          "target": "SELF",
          "applyCondition": {
            "type": "BuffHasTrait",
            "value": "NEGATIVE_BUFF"
          },
          "intValues": [0]
        }],
        "iconName": "starWeightUp"
      }, {
        "baseCoolDown": 7,
        "effects": [{
          "type": "GrantBuff",
          "target": "SELF",
          "buffData": [{
            "type": "CriticalStarWeightBuff",
            "numTurnsActive": 1,
            "values": [3.0, 3.2, 3.4, 3.6, 3.8, 4.0, 4.2, 4.4, 4.6, 5.0],
            "buffIcon": "starWeightUp"
          }]
        }, {
          "type": "GrantBuff",
          "target": "SELF",
          "buffData": [{
            "type": "SpecificAttackBuff",
            "numTurnsActive": 3,
            "applyCondition": {
              "type": "TargetsHaveTrait",
              "value": "DEMONIC",
              "target": "DEFENDER"
            },
            "values": [0.3, 0.32, 0.34, 0.36, 0.38, 0.4, 0.42, 0.44, 0.46, 0.5],
            "buffIcon": "specialDamageUp"
          }]
        }, {
          "type": "GrantBuff",
          "target": "SELF",
          "buffData": [{
            "type": "SpecificDefenseBuff",
            "numTurnsActive": 3,
            "applyCondition": {
              "type": "TargetsHaveTrait",
              "value": "DEMONIC",
              "target": "ATTACKER"
            },
            "values": [0.2, 0.21, 0.22, 0.23, 0.24, 0.25, 0.26, 0.27, 0.28, 0.3],
            "buffIcon": "defenseUp"
          }]
        }, {
          "type": "RemoveBuff",
          "target": "SELF",
          "applyCondition": {
            "type": "BuffHasTrait",
            "value": "NEGATIVE_BUFF"
          },
          "intValues": [0]
        }, {
          "type": "CriticalStarChange",
          "intValues": [5, 6, 7, 8, 9, 10, 11, 12, 13, 15]
        }],
        "iconName": "starWeightUp"
      }]
    }],
    "passiveSkillData": [{
      "effects": [{
        "type": "GrantBuff",
        "target": "SELF",
        "buffData": [{
          "type": "DebuffResist",
          "values": [0.2],
          "buffIcon": "debuffResistUp"
        }]
      }],
      "iconName": "magicResistance"
    }],
    "appendSkillData": [{
      "effects": [{
        "type": "GrantBuff",
        "target": "SELF",
        "buffData": [{
          "type": "CommandCardBuff",
          "applyCondition": {
            "type": "CardTypeEquals",
            "value": "EXTRA"
          },
          "values": [0.3, 0.32, 0.34, 0.36, 0.38, 0.4, 0.42, 0.44, 0.46, 0.5],
          "buffIcon": "specialDamageUp"
        }]
      }],
      "iconName": "specialAttackUp"
    }, {
      "effects": [{
        "type": "NpChange",
        "target": "SELF",
        "values": [0.1, 0.11, 0.12, 0.13, 0.14, 0.15, 0.16, 0.17, 0.18, 0.2]
      }],
      "iconName": "npGain"
    }, {
      "effects": [{
        "type": "GrantBuff",
        "target": "SELF",
        "buffData": [{
          "type": "AttackBuff",
          "applyCondition": {
            "type": "TargetsHaveClass",
            "value": "CASTER",
            "target": "DEFENDER"
          },
          "values": [0.2, 0.21, 0.22, 0.23, 0.24, 0.25, 0.26, 0.27, 0.28, 0.3],
          "buffIcon": "attackUp"
        }]
      }],
      "iconName": "attackUp"
    }],
    "servantStatusData": [{
      "lv": 1,
      "HP": 1938,
      "ATK": 1547
    }, {
      "lv": 2,
      "HP": 2060,
      "ATK": 1639
    }, {
      "lv": 3,
      "HP": 2192,
      "ATK": 1740
    }, {
      "lv": 4,
      "HP": 2314,
      "ATK": 1833
    }, {
      "lv": 5,
      "HP": 2446,
      "ATK": 1933
    }, {
      "lv": 6,
      "HP": 2578,
      "ATK": 2034
    }, {
      "lv": 7,
      "HP": 2701,
      "ATK": 2127
    }, {
      "lv": 8,
      "HP": 2833,
      "ATK": 2227
    }, {
      "lv": 9,
      "HP": 2965,
      "ATK": 2328
    }, {
      "lv": 10,
      "HP": 3087,
      "ATK": 2421
    }, {
      "lv": 11,
      "HP": 3219,
      "ATK": 2521
    }, {
      "lv": 12,
      "HP": 3352,
      "ATK": 2622
    }, {
      "lv": 13,
      "HP": 3474,
      "ATK": 2715
    }, {
      "lv": 14,
      "HP": 3606,
      "ATK": 2815
    }, {
      "lv": 15,
      "HP": 3738,
      "ATK": 2916
    }, {
      "lv": 16,
      "HP": 3860,
      "ATK": 3009
    }, {
      "lv": 17,
      "HP": 3993,
      "ATK": 3109
    }, {
      "lv": 18,
      "HP": 4125,
      "ATK": 3210
    }, {
      "lv": 19,
      "HP": 4247,
      "ATK": 3303
    }, {
      "lv": 20,
      "HP": 4379,
      "ATK": 3403
    }, {
      "lv": 21,
      "HP": 4512,
      "ATK": 3504
    }, {
      "lv": 22,
      "HP": 4634,
      "ATK": 3597
    }, {
      "lv": 23,
      "HP": 4766,
      "ATK": 3697
    }, {
      "lv": 24,
      "HP": 4898,
      "ATK": 3798
    }, {
      "lv": 25,
      "HP": 5020,
      "ATK": 3891
    }, {
      "lv": 26,
      "HP": 5152,
      "ATK": 3991
    }, {
      "lv": 27,
      "HP": 5285,
      "ATK": 4092
    }, {
      "lv": 28,
      "HP": 5407,
      "ATK": 4185
    }, {
      "lv": 29,
      "HP": 5539,
      "ATK": 4285
    }, {
      "lv": 30,
      "HP": 5671,
      "ATK": 4386
    }, {
      "lv": 31,
      "HP": 5793,
      "ATK": 4479
    }, {
      "lv": 32,
      "HP": 5926,
      "ATK": 4579
    }, {
      "lv": 33,
      "HP": 6058,
      "ATK": 4680
    }, {
      "lv": 34,
      "HP": 6180,
      "ATK": 4773
    }, {
      "lv": 35,
      "HP": 6312,
      "ATK": 4873
    }, {
      "lv": 36,
      "HP": 6445,
      "ATK": 4974
    }, {
      "lv": 37,
      "HP": 6567,
      "ATK": 5067
    }, {
      "lv": 38,
      "HP": 6699,
      "ATK": 5167
    }, {
      "lv": 39,
      "HP": 6831,
      "ATK": 5268
    }, {
      "lv": 40,
      "HP": 6953,
      "ATK": 5361
    }, {
      "lv": 41,
      "HP": 7086,
      "ATK": 5461
    }, {
      "lv": 42,
      "HP": 7208,
      "ATK": 5554
    }, {
      "lv": 43,
      "HP": 7340,
      "ATK": 5655
    }, {
      "lv": 44,
      "HP": 7472,
      "ATK": 5755
    }, {
      "lv": 45,
      "HP": 7594,
      "ATK": 5848
    }, {
      "lv": 46,
      "HP": 7727,
      "ATK": 5949
    }, {
      "lv": 47,
      "HP": 7859,
      "ATK": 6049
    }, {
      "lv": 48,
      "HP": 7981,
      "ATK": 6142
    }, {
      "lv": 49,
      "HP": 8113,
      "ATK": 6243
    }, {
      "lv": 50,
      "HP": 8245,
      "ATK": 6343
    }, {
      "lv": 51,
      "HP": 8367,
      "ATK": 6436
    }, {
      "lv": 52,
      "HP": 8500,
      "ATK": 6537
    }, {
      "lv": 53,
      "HP": 8632,
      "ATK": 6637
    }, {
      "lv": 54,
      "HP": 8754,
      "ATK": 6730
    }, {
      "lv": 55,
      "HP": 8886,
      "ATK": 6831
    }, {
      "lv": 56,
      "HP": 9019,
      "ATK": 6931
    }, {
      "lv": 57,
      "HP": 9141,
      "ATK": 7024
    }, {
      "lv": 58,
      "HP": 9273,
      "ATK": 7125
    }, {
      "lv": 59,
      "HP": 9405,
      "ATK": 7225
    }, {
      "lv": 60,
      "HP": 9527,
      "ATK": 7318
    }, {
      "lv": 61,
      "HP": 9660,
      "ATK": 7419
    }, {
      "lv": 62,
      "HP": 9792,
      "ATK": 7519
    }, {
      "lv": 63,
      "HP": 9914,
      "ATK": 7612
    }, {
      "lv": 64,
      "HP": 10046,
      "ATK": 7713
    }, {
      "lv": 65,
      "HP": 10178,
      "ATK": 7813
    }, {
      "lv": 66,
      "HP": 10301,
      "ATK": 7906
    }, {
      "lv": 67,
      "HP": 10433,
      "ATK": 8007
    }, {
      "lv": 68,
      "HP": 10565,
      "ATK": 8107
    }, {
      "lv": 69,
      "HP": 10687,
      "ATK": 8200
    }, {
      "lv": 70,
      "HP": 10819,
      "ATK": 8301
    }, {
      "lv": 71,
      "HP": 10952,
      "ATK": 8401
    }, {
      "lv": 72,
      "HP": 11074,
      "ATK": 8494
    }, {
      "lv": 73,
      "HP": 11206,
      "ATK": 8595
    }, {
      "lv": 74,
      "HP": 11338,
      "ATK": 8695
    }, {
      "lv": 75,
      "HP": 11460,
      "ATK": 8788
    }, {
      "lv": 76,
      "HP": 11593,
      "ATK": 8889
    }, {
      "lv": 77,
      "HP": 11725,
      "ATK": 8989
    }, {
      "lv": 78,
      "HP": 11847,
      "ATK": 9082
    }, {
      "lv": 79,
      "HP": 11979,
      "ATK": 9183
    }, {
      "lv": 80,
      "HP": 12112,
      "ATK": 9284
    }, {
      "lv": 81,
      "HP": 12234,
      "ATK": 9376
    }, {
      "lv": 82,
      "HP": 12366,
      "ATK": 9477
    }, {
      "lv": 83,
      "HP": 12488,
      "ATK": 9570
    }, {
      "lv": 84,
      "HP": 12620,
      "ATK": 9670
    }, {
      "lv": 85,
      "HP": 12752,
      "ATK": 9771
    }, {
      "lv": 86,
      "HP": 12875,
      "ATK": 9864
    }, {
      "lv": 87,
      "HP": 13007,
      "ATK": 9964
    }, {
      "lv": 88,
      "HP": 13139,
      "ATK": 10065
    }, {
      "lv": 89,
      "HP": 13261,
      "ATK": 10158
    }, {
      "lv": 90,
      "HP": 13393,
      "ATK": 10258
    }, {
      "lv": 91,
      "HP": 13526,
      "ATK": 10359
    }, {
      "lv": 92,
      "HP": 13648,
      "ATK": 10452
    }, {
      "lv": 93,
      "HP": 13780,
      "ATK": 10552
    }, {
      "lv": 94,
      "HP": 13912,
      "ATK": 10653
    }, {
      "lv": 95,
      "HP": 14034,
      "ATK": 10746
    }, {
      "lv": 96,
      "HP": 14167,
      "ATK": 10846
    }, {
      "lv": 97,
      "HP": 14299,
      "ATK": 10947
    }, {
      "lv": 98,
      "HP": 14421,
      "ATK": 11040
    }, {
      "lv": 99,
      "HP": 14553,
      "ATK": 11140
    }, {
      "lv": 100,
      "HP": 14686,
      "ATK": 11241
    }, {
      "lv": 101,
      "HP": 14808,
      "ATK": 11334
    }, {
      "lv": 102,
      "HP": 14940,
      "ATK": 11434
    }, {
      "lv": 103,
      "HP": 15072,
      "ATK": 11535
    }, {
      "lv": 104,
      "HP": 15194,
      "ATK": 11628
    }, {
      "lv": 105,
      "HP": 15326,
      "ATK": 11728
    }, {
      "lv": 106,
      "HP": 15459,
      "ATK": 11829
    }, {
      "lv": 107,
      "HP": 15581,
      "ATK": 11922
    }, {
      "lv": 108,
      "HP": 15713,
      "ATK": 12022
    }, {
      "lv": 109,
      "HP": 15845,
      "ATK": 12123
    }, {
      "lv": 110,
      "HP": 15967,
      "ATK": 12216
    }, {
      "lv": 111,
      "HP": 16100,
      "ATK": 12316
    }, {
      "lv": 112,
      "HP": 16232,
      "ATK": 12417
    }, {
      "lv": 113,
      "HP": 16354,
      "ATK": 12510
    }, {
      "lv": 114,
      "HP": 16486,
      "ATK": 12610
    }, {
      "lv": 115,
      "HP": 16619,
      "ATK": 12711
    }, {
      "lv": 116,
      "HP": 16741,
      "ATK": 12804
    }, {
      "lv": 117,
      "HP": 16873,
      "ATK": 12904
    }, {
      "lv": 118,
      "HP": 17005,
      "ATK": 13005
    }, {
      "lv": 119,
      "HP": 17127,
      "ATK": 13098
    }, {
      "lv": 120,
      "HP": 17260,
      "ATK": 13198
    }],
    "noblePhantasmUpgrades": {
      "noblePhantasmData": [{
        "commandCardData": {
          "commandCardType": "BUSTER",
          "hitsData": [16, 33, 51],
          "npRate": 0.0072,
          "criticalStarGen": 0.122
        },
        "effects": [{
          "type": "GrantBuff",
          "target": "SELF",
          "isOverchargedEffect": true,
          "buffData": [{
            "type": "NpDamageBuff",
            "numTurnsActive": 1,
            "values": [0.2],
            "buffIcon": "npDamageUp"
          }, {
            "type": "NpDamageBuff",
            "numTurnsActive": 1,
            "values": [0.3],
            "buffIcon": "npDamageUp"
          }, {
            "type": "NpDamageBuff",
            "numTurnsActive": 1,
            "values": [0.4],
            "buffIcon": "npDamageUp"
          }, {
            "type": "NpDamageBuff",
            "numTurnsActive": 1,
            "values": [0.5],
            "buffIcon": "npDamageUp"
          }, {
            "type": "NpDamageBuff",
            "numTurnsActive": 1,
            "values": [0.6],
            "buffIcon": "npDamageUp"
          }]
        }, {
          "type": "NoblePhantasmDamage",
          "target": "ALL_ENEMIES",
          "values": [3.0, 4.0, 4.5, 4.75, 5.0]
        }, {
          "type": "GrantBuff",
          "target": "ALL_ENEMIES",
          "buffData": [{
            "type": "Burn",
            "numTurnsActive": 5,
            "values": [1000.0],
            "buffIcon": "burn"
          }]
        }],
        "noblePhantasmType": "ALL_TARGETS_NP"
      }, {
        "commandCardData": {
          "commandCardType": "BUSTER",
          "hitsData": [16, 33, 51],
          "npRate": 0.0072,
          "criticalStarGen": 0.122
        },
        "effects": [{
          "type": "GrantBuff",
          "target": "SELF",
          "isOverchargedEffect": true,
          "buffData": [{
            "type": "NpDamageBuff",
            "numTurnsActive": 1,
            "values": [0.2],
            "buffIcon": "npDamageUp"
          }, {
            "type": "NpDamageBuff",
            "numTurnsActive": 1,
            "values": [0.3],
            "buffIcon": "npDamageUp"
          }, {
            "type": "NpDamageBuff",
            "numTurnsActive": 1,
            "values": [0.4],
            "buffIcon": "npDamageUp"
          }, {
            "type": "NpDamageBuff",
            "numTurnsActive": 1,
            "values": [0.5],
            "buffIcon": "npDamageUp"
          }, {
            "type": "NpDamageBuff",
            "numTurnsActive": 1,
            "values": [0.6],
            "buffIcon": "npDamageUp"
          }]
        }, {
          "type": "NoblePhantasmDamage",
          "target": "ALL_ENEMIES",
          "values": [4.0, 5.0, 5.5, 5.75, 6.0]
        }, {
          "type": "GrantBuff",
          "target": "ALL_ENEMIES",
          "buffData": [{
            "type": "Burn",
            "numTurnsActive": 5,
            "values": [3000.0],
            "buffIcon": "burn"
          }]
        }],
        "noblePhantasmType": "ALL_TARGETS_NP"
      }]
    },
    "extraCard": {
      "commandCardType": "EXTRA",
      "hitsData": [10, 20, 30, 40],
      "npRate": 0.0072,
      "criticalStarGen": 0.122
    },
    "cost": 12
  }],
  "servantNum": 193
}
