{
  "servantAscensionData": [{
    "combatantData": {
      "id": "servant327",
      "rarity": 5,
      "fateClass": "CASTER",
      "gender": "FEMALE",
      "alignments": ["CHAOTIC", "GOOD"],
      "attribute": "MAN",
      "traits": ["HOMINIDAE_SERVANT", "HUMANOID", "WEAK_TO_ENUMA_ELISH"],
      "deathRate": 0.42
    },
    "defenseNpRate": 0.03,
    "criticalStarWeight": 51,
    "commandCardData": [{
      "commandCardType": "QUICK",
      "hitsData": [10, 20, 30, 40],
      "npRate": 0.008,
      "criticalStarGen": 0.109
    }, {
      "commandCardType": "QUICK",
      "hitsData": [10, 20, 30, 40],
      "npRate": 0.008,
      "criticalStarGen": 0.109
    }, {
      "commandCardType": "ARTS",
      "hitsData": [16, 33, 51],
      "npRate": 0.008,
      "criticalStarGen": 0.109
    }, {
      "commandCardType": "ARTS",
      "hitsData": [16, 33, 51],
      "npRate": 0.008,
      "criticalStarGen": 0.109
    }, {
      "commandCardType": "BUSTER",
      "hitsData": [16, 33, 51],
      "npRate": 0.008,
      "criticalStarGen": 0.109
    }],
    "activeSkillUpgrades": [{
      "activeSkillData": [{
        "baseCoolDown": 9,
        "effects": [{
          "type": "GrantBuff",
          "target": "SELF",
          "buffData": [{
            "type": "CommandCardBuff",
            "numTurnsActive": 3,
            "applyCondition": {
              "type": "CardTypeEquals",
              "value": "QUICK"
            },
            "values": [0.2, 0.21, 0.22, 0.23, 0.24, 0.25, 0.26, 0.27, 0.28, 0.3],
            "buffIcon": "quickUp"
          }]
        }, {
          "type": "GrantBuff",
          "target": "SELF",
          "buffData": [{
            "type": "CommandCardBuff",
            "numTurnsActive": 3,
            "applyCondition": {
              "type": "CardTypeEquals",
              "value": "BUSTER"
            },
            "values": [0.2, 0.21, 0.22, 0.23, 0.24, 0.25, 0.26, 0.27, 0.28, 0.3],
            "buffIcon": "busterUp"
          }]
        }, {
          "type": "GrantBuff",
          "target": "SELF",
          "buffData": [{
            "type": "Evade",
            "numTurnsActive": 3,
            "numTimesActive": 2,
            "buffIcon": "evade"
          }]
        }],
        "iconName": "quickBusterUp"
      }]
    }, {
      "activeSkillData": [{
        "baseCoolDown": 7,
        "effects": [{
          "type": "GrantBuff",
          "target": "SELF",
          "buffData": [{
            "type": "CriticalStarWeightBuff",
            "numTurnsActive": 1,
            "values": [6.0, 6.4, 6.8, 7.2, 7.6, 8.0, 8.4, 8.8, 9.2, 10.0],
            "buffIcon": "starWeightUp"
          }]
        }, {
          "type": "GrantBuff",
          "target": "SELF",
          "buffData": [{
            "type": "CriticalDamageBuff",
            "numTurnsActive": 1,
            "values": [0.5, 0.55, 0.6, 0.65, 0.7, 0.75, 0.8, 0.85, 0.9, 1.0],
            "buffIcon": "critDamageUp"
          }]
        }, {
          "type": "GrantBuff",
          "target": "SELF",
          "buffData": [{
            "type": "PostAttackEffect",
            "numTurnsActive": 1,
            "applyCondition": {
              "type": "IsCriticalStrike"
            },
            "subEffects": [{
              "type": "GrantBuff",
              "target": "DEFENDER",
              "buffData": [{
                "type": "DefenseBuff",
                "numTurnsActive": 3,
                "values": [-0.1],
                "buffIcon": "defenseDown"
              }]
            }],
            "customTraits": ["POSITIVE_BUFF"],
            "hasCustomTraits": true,
            "buffIcon": "attackApplyDebuff"
          }]
        }],
        "iconName": "starWeightUp"
      }]
    }, {
      "activeSkillData": [{
        "baseCoolDown": 9,
        "effects": [{
          "type": "DecreaseActiveSkillCoolDown",
          "target": "TARGETED_ALLY",
          "intValues": [1]
        }, {
          "type": "NpChange",
          "target": "SELF",
          "values": [0.3, 0.32, 0.34, 0.36, 0.38, 0.4, 0.42, 0.44, 0.46, 0.5]
        }, {
          "type": "CriticalStarChange",
          "intValues": [5, 6, 7, 8, 9, 10, 11, 12, 13, 15]
        }],
        "iconName": "coolDownDecrease"
      }]
    }],
    "passiveSkillData": [{
      "effects": [{
        "type": "GrantBuff",
        "target": "SELF",
        "buffData": [{
          "type": "CommandCardBuff",
          "applyCondition": {
            "type": "CardTypeEquals",
            "value": "ARTS"
          },
          "values": [0.04],
          "buffIcon": "artsUp"
        }]
      }, {
        "type": "GrantBuff",
        "target": "SELF",
        "buffData": [{
          "type": "CriticalDamageBuff",
          "values": [0.04],
          "buffIcon": "critDamageUp"
        }]
      }],
      "iconName": "territoryCreation"
    }, {
      "effects": [{
        "type": "GrantBuff",
        "target": "SELF",
        "buffData": [{
          "type": "DebuffChanceBuff",
          "values": [0.04],
          "buffIcon": "buffChanceUp"
        }]
      }, {
        "type": "GrantBuff",
        "target": "SELF",
        "buffData": [{
          "type": "CriticalDamageBuff",
          "values": [0.04],
          "buffIcon": "critDamageUp"
        }]
      }],
      "iconName": "itemConstruction"
    }, {
      "effects": [{
        "type": "GrantBuff",
        "target": "SELF",
        "buffData": [{
          "type": "EndOfTurnEffect",
          "subEffects": [{
            "type": "CriticalStarChange",
            "intValues": [2]
          }],
          "customTraits": ["POSITIVE_BUFF"],
          "hasCustomTraits": true,
          "buffIcon": "starsPerTurn"
        }]
      }, {
        "type": "GrantBuff",
        "target": "SELF",
        "buffData": [{
          "type": "CriticalDamageBuff",
          "values": [0.04],
          "buffIcon": "critDamageUp"
        }]
      }],
      "iconName": "gainStarPerTurn"
    }],
    "appendSkillData": [{
      "effects": [{
        "type": "GrantBuff",
        "target": "SELF",
        "buffData": [{
          "type": "CommandCardBuff",
          "applyCondition": {
            "type": "CardTypeEquals",
            "value": "EXTRA"
          },
          "values": [0.3, 0.32, 0.34, 0.36, 0.38, 0.4, 0.42, 0.44, 0.46, 0.5],
          "buffIcon": "specialDamageUp"
        }]
      }],
      "iconName": "specialAttackUp"
    }, {
      "effects": [{
        "type": "NpChange",
        "target": "SELF",
        "values": [0.1, 0.11, 0.12, 0.13, 0.14, 0.15, 0.16, 0.17, 0.18, 0.2]
      }],
      "iconName": "npGain"
    }, {
      "effects": [{
        "type": "GrantBuff",
        "target": "SELF",
        "buffData": [{
          "type": "AttackBuff",
          "applyCondition": {
            "type": "TargetsHaveClass",
            "value": "PRETENDER",
            "target": "DEFENDER"
          },
          "values": [0.2, 0.21, 0.22, 0.23, 0.24, 0.25, 0.26, 0.27, 0.28, 0.3],
          "buffIcon": "attackUp"
        }]
      }],
      "iconName": "attackUp"
    }],
    "servantStatusData": [{
      "lv": 1,
      "HP": 1901,
      "ATK": 1757
    }, {
      "lv": 2,
      "HP": 2022,
      "ATK": 1862
    }, {
      "lv": 3,
      "HP": 2144,
      "ATK": 1968
    }, {
      "lv": 4,
      "HP": 2266,
      "ATK": 2074
    }, {
      "lv": 5,
      "HP": 2387,
      "ATK": 2180
    }, {
      "lv": 6,
      "HP": 2520,
      "ATK": 2295
    }, {
      "lv": 7,
      "HP": 2642,
      "ATK": 2401
    }, {
      "lv": 8,
      "HP": 2763,
      "ATK": 2507
    }, {
      "lv": 9,
      "HP": 2885,
      "ATK": 2612
    }, {
      "lv": 10,
      "HP": 3018,
      "ATK": 2728
    }, {
      "lv": 11,
      "HP": 3140,
      "ATK": 2834
    }, {
      "lv": 12,
      "HP": 3261,
      "ATK": 2939
    }, {
      "lv": 13,
      "HP": 3383,
      "ATK": 3045
    }, {
      "lv": 14,
      "HP": 3516,
      "ATK": 3161
    }, {
      "lv": 15,
      "HP": 3638,
      "ATK": 3266
    }, {
      "lv": 16,
      "HP": 3759,
      "ATK": 3372
    }, {
      "lv": 17,
      "HP": 3881,
      "ATK": 3478
    }, {
      "lv": 18,
      "HP": 4014,
      "ATK": 3593
    }, {
      "lv": 19,
      "HP": 4135,
      "ATK": 3699
    }, {
      "lv": 20,
      "HP": 4257,
      "ATK": 3805
    }, {
      "lv": 21,
      "HP": 4379,
      "ATK": 3911
    }, {
      "lv": 22,
      "HP": 4501,
      "ATK": 4016
    }, {
      "lv": 23,
      "HP": 4633,
      "ATK": 4132
    }, {
      "lv": 24,
      "HP": 4755,
      "ATK": 4238
    }, {
      "lv": 25,
      "HP": 4877,
      "ATK": 4343
    }, {
      "lv": 26,
      "HP": 4998,
      "ATK": 4449
    }, {
      "lv": 27,
      "HP": 5131,
      "ATK": 4565
    }, {
      "lv": 28,
      "HP": 5253,
      "ATK": 4670
    }, {
      "lv": 29,
      "HP": 5375,
      "ATK": 4776
    }, {
      "lv": 30,
      "HP": 5496,
      "ATK": 4882
    }, {
      "lv": 31,
      "HP": 5629,
      "ATK": 4997
    }, {
      "lv": 32,
      "HP": 5751,
      "ATK": 5103
    }, {
      "lv": 33,
      "HP": 5872,
      "ATK": 5209
    }, {
      "lv": 34,
      "HP": 5994,
      "ATK": 5315
    }, {
      "lv": 35,
      "HP": 6127,
      "ATK": 5430
    }, {
      "lv": 36,
      "HP": 6249,
      "ATK": 5536
    }, {
      "lv": 37,
      "HP": 6370,
      "ATK": 5642
    }, {
      "lv": 38,
      "HP": 6492,
      "ATK": 5748
    }, {
      "lv": 39,
      "HP": 6614,
      "ATK": 5853
    }, {
      "lv": 40,
      "HP": 6747,
      "ATK": 5969
    }, {
      "lv": 41,
      "HP": 6868,
      "ATK": 6075
    }, {
      "lv": 42,
      "HP": 6990,
      "ATK": 6180
    }, {
      "lv": 43,
      "HP": 7112,
      "ATK": 6286
    }, {
      "lv": 44,
      "HP": 7244,
      "ATK": 6402
    }, {
      "lv": 45,
      "HP": 7366,
      "ATK": 6507
    }, {
      "lv": 46,
      "HP": 7488,
      "ATK": 6613
    }, {
      "lv": 47,
      "HP": 7610,
      "ATK": 6719
    }, {
      "lv": 48,
      "HP": 7742,
      "ATK": 6834
    }, {
      "lv": 49,
      "HP": 7864,
      "ATK": 6940
    }, {
      "lv": 50,
      "HP": 7986,
      "ATK": 7046
    }, {
      "lv": 51,
      "HP": 8107,
      "ATK": 7152
    }, {
      "lv": 52,
      "HP": 8240,
      "ATK": 7267
    }, {
      "lv": 53,
      "HP": 8362,
      "ATK": 7373
    }, {
      "lv": 54,
      "HP": 8484,
      "ATK": 7479
    }, {
      "lv": 55,
      "HP": 8605,
      "ATK": 7584
    }, {
      "lv": 56,
      "HP": 8727,
      "ATK": 7690
    }, {
      "lv": 57,
      "HP": 8860,
      "ATK": 7806
    }, {
      "lv": 58,
      "HP": 8981,
      "ATK": 7911
    }, {
      "lv": 59,
      "HP": 9103,
      "ATK": 8017
    }, {
      "lv": 60,
      "HP": 9225,
      "ATK": 8123
    }, {
      "lv": 61,
      "HP": 9358,
      "ATK": 8238
    }, {
      "lv": 62,
      "HP": 9479,
      "ATK": 8344
    }, {
      "lv": 63,
      "HP": 9601,
      "ATK": 8450
    }, {
      "lv": 64,
      "HP": 9723,
      "ATK": 8556
    }, {
      "lv": 65,
      "HP": 9856,
      "ATK": 8671
    }, {
      "lv": 66,
      "HP": 9977,
      "ATK": 8777
    }, {
      "lv": 67,
      "HP": 10099,
      "ATK": 8883
    }, {
      "lv": 68,
      "HP": 10221,
      "ATK": 8988
    }, {
      "lv": 69,
      "HP": 10353,
      "ATK": 9104
    }, {
      "lv": 70,
      "HP": 10475,
      "ATK": 9210
    }, {
      "lv": 71,
      "HP": 10597,
      "ATK": 9315
    }, {
      "lv": 72,
      "HP": 10719,
      "ATK": 9421
    }, {
      "lv": 73,
      "HP": 10840,
      "ATK": 9527
    }, {
      "lv": 74,
      "HP": 10973,
      "ATK": 9642
    }, {
      "lv": 75,
      "HP": 11095,
      "ATK": 9748
    }, {
      "lv": 76,
      "HP": 11216,
      "ATK": 9854
    }, {
      "lv": 77,
      "HP": 11338,
      "ATK": 9960
    }, {
      "lv": 78,
      "HP": 11471,
      "ATK": 10075
    }, {
      "lv": 79,
      "HP": 11593,
      "ATK": 10181
    }, {
      "lv": 80,
      "HP": 11714,
      "ATK": 10287
    }, {
      "lv": 81,
      "HP": 11836,
      "ATK": 10393
    }, {
      "lv": 82,
      "HP": 11969,
      "ATK": 10508
    }, {
      "lv": 83,
      "HP": 12090,
      "ATK": 10614
    }, {
      "lv": 84,
      "HP": 12212,
      "ATK": 10720
    }, {
      "lv": 85,
      "HP": 12334,
      "ATK": 10825
    }, {
      "lv": 86,
      "HP": 12467,
      "ATK": 10941
    }, {
      "lv": 87,
      "HP": 12588,
      "ATK": 11047
    }, {
      "lv": 88,
      "HP": 12710,
      "ATK": 11152
    }, {
      "lv": 89,
      "HP": 12832,
      "ATK": 11258
    }, {
      "lv": 90,
      "HP": 12965,
      "ATK": 11374
    }, {
      "lv": 91,
      "HP": 13086,
      "ATK": 11479
    }, {
      "lv": 92,
      "HP": 13208,
      "ATK": 11585
    }, {
      "lv": 93,
      "HP": 13330,
      "ATK": 11691
    }, {
      "lv": 94,
      "HP": 13451,
      "ATK": 11797
    }, {
      "lv": 95,
      "HP": 13584,
      "ATK": 11912
    }, {
      "lv": 96,
      "HP": 13706,
      "ATK": 12018
    }, {
      "lv": 97,
      "HP": 13827,
      "ATK": 12124
    }, {
      "lv": 98,
      "HP": 13949,
      "ATK": 12229
    }, {
      "lv": 99,
      "HP": 14082,
      "ATK": 12345
    }, {
      "lv": 100,
      "HP": 14204,
      "ATK": 12451
    }, {
      "lv": 101,
      "HP": 14325,
      "ATK": 12556
    }, {
      "lv": 102,
      "HP": 14447,
      "ATK": 12662
    }, {
      "lv": 103,
      "HP": 14580,
      "ATK": 12778
    }, {
      "lv": 104,
      "HP": 14702,
      "ATK": 12883
    }, {
      "lv": 105,
      "HP": 14823,
      "ATK": 12989
    }, {
      "lv": 106,
      "HP": 14945,
      "ATK": 13095
    }, {
      "lv": 107,
      "HP": 15078,
      "ATK": 13210
    }, {
      "lv": 108,
      "HP": 15199,
      "ATK": 13316
    }, {
      "lv": 109,
      "HP": 15321,
      "ATK": 13422
    }, {
      "lv": 110,
      "HP": 15443,
      "ATK": 13528
    }, {
      "lv": 111,
      "HP": 15565,
      "ATK": 13633
    }, {
      "lv": 112,
      "HP": 15697,
      "ATK": 13749
    }, {
      "lv": 113,
      "HP": 15819,
      "ATK": 13855
    }, {
      "lv": 114,
      "HP": 15941,
      "ATK": 13960
    }, {
      "lv": 115,
      "HP": 16062,
      "ATK": 14066
    }, {
      "lv": 116,
      "HP": 16195,
      "ATK": 14182
    }, {
      "lv": 117,
      "HP": 16317,
      "ATK": 14287
    }, {
      "lv": 118,
      "HP": 16439,
      "ATK": 14393
    }, {
      "lv": 119,
      "HP": 16560,
      "ATK": 14499
    }, {
      "lv": 120,
      "HP": 16693,
      "ATK": 14614
    }],
    "noblePhantasmUpgrades": {
      "noblePhantasmData": [{
        "commandCardData": {
          "commandCardType": "QUICK",
          "hitsData": [1, 3, 5, 7, 9, 10, 12, 14, 16, 23],
          "npRate": 0.008,
          "criticalStarGen": 0.109
        },
        "effects": [{
          "type": "GrantBuff",
          "target": "TARGETED_ENEMY",
          "buffData": [{
            "type": "CommandCardResist",
            "numTurnsActive": 3,
            "applyCondition": {
              "type": "CardTypeEquals",
              "value": "QUICK"
            },
            "values": [-0.2],
            "buffIcon": "quickResistDown"
          }]
        }, {
          "type": "NoblePhantasmDamage",
          "target": "TARGETED_ENEMY",
          "values": [12.0, 16.0, 18.0, 19.0, 20.0],
          "npDamageAdditionalParams": {
            "npSpecificDamageCondition": {
              "type": "TargetsHaveTrait",
              "value": "DEMONIC",
              "target": "DEFENDER"
            },
            "isNpSpecificDamageOverchargedEffect": true,
            "npSpecificDamageRate": [1.5, 1.625, 1.75, 1.875, 2.0]
          }
        }],
        "noblePhantasmType": "SINGLE_TARGET_NP"
      }]
    },
    "extraCard": {
      "commandCardType": "EXTRA",
      "hitsData": [6, 13, 20, 26, 35],
      "npRate": 0.008,
      "criticalStarGen": 0.109
    },
    "cost": 16
  }],
  "servantNum": 327
}
