{
  "buffs": [{
    "type": "PreAttackEffect",
    "subEffects": [{
      "type": "RemoveBuff",
      "target": "DEFENDER",
      "values": [1.0],
      "applyCondition": {
        "type": "And",
        "subConditionData": [{
          "type": "BuffTypeEquals",
          "value": "AttackBuff"
        }, {
          "type": "BuffHasTrait",
          "value": "POSITIVE_BUFF"
        }]
      }
    }, {
      "type": "HpChange",
      "target": "ATTACKER",
      "intValues": [100]
    }],
    "customTraits": ["POSITIVE_BUFF", "ATTACKER_BUFF"],
    "hasCustomTraits": true,
    "buffIcon": "attackApplyBuff"
  }],
  "id": "commandCode28",
  "ccNum": 28,
  "rarity": 3
}
